ocw_data_parser/__init__.py
ocw_data_parser/conftest.py
ocw_data_parser/course_downloader.py
ocw_data_parser/course_downloader_test.py
ocw_data_parser/course_feature_tags.py
ocw_data_parser/ocw_data_parser.py
ocw_data_parser/ocw_data_parser_test.py
ocw_data_parser/test_constants.py
ocw_data_parser/utils.py
ocw_data_parser/utils_test.py
ocw_data_parser-0.35.1.dist-info/METADATA
ocw_data_parser-0.35.1.dist-info/WHEEL
ocw_data_parser-0.35.1.dist-info/top_level.txt
ocw_data_parser-0.35.1.dist-info/RECORD
