Metadata-Version: 2.1
Name: ocw-data-parser
Version: 0.35.1
Summary: a parsing library for OpenCourseWare json exports
Home-page: https://github.com/zagaran/ocw-data-parser
Author: Zagaran, Inc.
Author-email: UNKNOWN
License: To be determined
Platform: UNKNOWN
Requires-Dist: boto3 (>=1.9.62)
Requires-Dist: requests (>=2.21.0)
Requires-Dist: smart-open (>=1.8.0)
Requires-Dist: webvtt-py (==0.4.6)
